SichengZhidaoFlaskJiaochengFix1/README.md
SichengZhidaoFlaskJiaochengFix1/__init__.py
SichengZhidaoFlaskJiaochengFix1/__main__.py
SichengZhidaoFlaskJiaochengFix1/file.epub
SichengZhidaoFlaskJiaochengFix1/index.html
SichengZhidaoFlaskJiaochengFix1/css/__init__.py
SichengZhidaoFlaskJiaochengFix1/css/annotations.css
SichengZhidaoFlaskJiaochengFix1/css/main.css
SichengZhidaoFlaskJiaochengFix1/css/normalize.css
SichengZhidaoFlaskJiaochengFix1/css/popup.css
SichengZhidaoFlaskJiaochengFix1/font/__init__.py
SichengZhidaoFlaskJiaochengFix1/font/fontello.eot
SichengZhidaoFlaskJiaochengFix1/font/fontello.svg
SichengZhidaoFlaskJiaochengFix1/font/fontello.ttf
SichengZhidaoFlaskJiaochengFix1/font/fontello.woff
SichengZhidaoFlaskJiaochengFix1/img/__init__.py
SichengZhidaoFlaskJiaochengFix1/img/annotator-glyph-sprite.png
SichengZhidaoFlaskJiaochengFix1/img/annotator-icon-sprite.png
SichengZhidaoFlaskJiaochengFix1/img/apple-touch-icon.png
SichengZhidaoFlaskJiaochengFix1/img/cancelfullscreen.png
SichengZhidaoFlaskJiaochengFix1/img/close.png
SichengZhidaoFlaskJiaochengFix1/img/fullscreen.png
SichengZhidaoFlaskJiaochengFix1/img/loader.gif
SichengZhidaoFlaskJiaochengFix1/img/menu-icon.png
SichengZhidaoFlaskJiaochengFix1/img/save.png
SichengZhidaoFlaskJiaochengFix1/img/saved.png
SichengZhidaoFlaskJiaochengFix1/img/settings-s.png
SichengZhidaoFlaskJiaochengFix1/img/settings.png
SichengZhidaoFlaskJiaochengFix1/img/star.png
SichengZhidaoFlaskJiaochengFix1/js/__init__.py
SichengZhidaoFlaskJiaochengFix1/js/epub.js
SichengZhidaoFlaskJiaochengFix1/js/epub.min.js
SichengZhidaoFlaskJiaochengFix1/js/epub.min.map
SichengZhidaoFlaskJiaochengFix1/js/hooks.min.js
SichengZhidaoFlaskJiaochengFix1/js/hooks.min.map
SichengZhidaoFlaskJiaochengFix1/js/reader.js
SichengZhidaoFlaskJiaochengFix1/js/reader.js.map
SichengZhidaoFlaskJiaochengFix1/js/reader.min.js
SichengZhidaoFlaskJiaochengFix1/js/reader.min.map
SichengZhidaoFlaskJiaochengFix1/js/hooks/__init__.py
sicheng_zhidao_flask_jiaocheng_fix1-2024.3.2.0.dist-info/METADATA
sicheng_zhidao_flask_jiaocheng_fix1-2024.3.2.0.dist-info/WHEEL
sicheng_zhidao_flask_jiaocheng_fix1-2024.3.2.0.dist-info/entry_points.txt
sicheng_zhidao_flask_jiaocheng_fix1-2024.3.2.0.dist-info/top_level.txt
sicheng_zhidao_flask_jiaocheng_fix1-2024.3.2.0.dist-info/RECORD
